LICENSE
MANIFEST.in
README.md
VERSION
requirements.txt
setup.cfg
setup.py
databases_watcher/__init__.py
databases_watcher/config.py
databases_watcher/connect_async.py
databases_watcher/connect_sync.py
databases_watcher/exceptions.py
databases_watcher/interfaces.py
databases_watcher/json_utils.py
databases_watcher.egg-info/PKG-INFO
databases_watcher.egg-info/SOURCES.txt
databases_watcher.egg-info/dependency_links.txt
databases_watcher.egg-info/requires.txt
databases_watcher.egg-info/top_level.txt
databases_watcher.egg-info/zip-safe
databases_watcher/databases/__init__.py
databases_watcher/databases/redis.py
databases_watcher/databases/redis_async.py
databases_watcher/databases/redis_config.py