Metadata-Version: 2.1
Name: databases-watcher
Version: 1.0.0
Summary: Multi database watcher for changes on them
Home-page: https://github.com/cr0hn/python-database-watcher
Author: Daniel Garcia
Maintainer: Daniel Garcia (cr0hn)
Maintainer-email: cr0hn@cr0hn.com
License: License :: OSI Approved :: MIT License
Platform: UNKNOWN
Classifier: License :: OSI Approved :: MIT License
Classifier: Programming Language :: Python :: 3.8
Classifier: Programming Language :: Python :: 3.9
Classifier: Programming Language :: Python :: 3.10
Classifier: Programming Language :: Python :: 3.11
Classifier: Environment :: Console
Classifier: Operating System :: POSIX
Classifier: Operating System :: MacOS
Classifier: Operating System :: OS Independent
Classifier: Operating System :: Microsoft :: Windows
